rs_metrics/__init__.py
rs_metrics/helpers.py
rs_metrics/metrics.py
rs_metrics/parallel.py
rs_metrics/statistics.py
rs_metrics-0.5.1.dist-info/METADATA
rs_metrics-0.5.1.dist-info/WHEEL
rs_metrics-0.5.1.dist-info/top_level.txt
rs_metrics-0.5.1.dist-info/RECORD
