Metadata-Version: 2.1
Name: rs-metrics
Version: 0.5.1
Summary: Metrics for recommender systems
Home-page: https://github.com/darel13712/rs_metrics
Author: Darel
Author-email: darel142857@gmail.com
Classifier: Programming Language :: Python :: 3
Classifier: License :: OSI Approved :: MIT License
Classifier: Operating System :: OS Independent
Requires-Python: >=3.6
Requires-Dist: pandas
Requires-Dist: numpy
